somepackk/__init__.py
somepackk/__main__.py
somepackk-1.1.dist-info/DESCRIPTION.rst
somepackk-1.1.dist-info/METADATA
somepackk-1.1.dist-info/RECORD
somepackk-1.1.dist-info/WHEEL
somepackk-1.1.dist-info/metadata.json
somepackk-1.1.dist-info/top_level.txt
