Metadata-Version: 2.0
Name: somepackk
Version: 1.1
Summary: A package that makes it easy to create Pypi packages
Home-page: UNKNOWN
Author: 
Author-email: 
License: UNKNOWN
Platform: UNKNOWN
Classifier: Programming Language :: Python :: 3
Classifier: License :: OSI Approved :: MIT License
Classifier: Operating System :: OS Independent
